market_profile/__init__.py
market_profile/utils.py
MarketProfile-0.2.0.dist-info/LICENSE
MarketProfile-0.2.0.dist-info/METADATA
MarketProfile-0.2.0.dist-info/WHEEL
MarketProfile-0.2.0.dist-info/top_level.txt
MarketProfile-0.2.0.dist-info/RECORD
